[{"@module": "pymatgen.entries.computed_entries", "@class": "ComputedStructureEntry", "energy": -24.1213708, "composition": {"Cd": 6.0, "Os": 2.0}, "entry_id": "mp-1183653-GGA", "correction": 0.0, "energy_adjustments": [], "parameters": {"potcar_spec": [{"titel": "PAW_PBE Cd 06Sep2000", "hash": "0506b2d0ac28d5fe2b5ced77a701aa86", "summary_stats": null}, {"titel": "PAW_PBE Os_pv 20Jan2003", "hash": "7bb96cace1809ebeb4d030d71024c5bf", "summary_stats": null}], "run_type": "GGA", "is_hubbard": false, "hubbards": null}, "structure": {"@module": "pymatgen.core.structure", "@class": "Structure", "charge": 0, "lattice": {"matrix": [[2.990935, -5.180451, 0.0], [2.990935, 5.180451, 0.0], [0.0, 0.0, 4.859414]], "pbc": [true, true, true], "a": 5.981869669060502, "b": 5.981869669060502, "c": 4.859414, "alpha": 90.0, "beta": 90.0, "gamma": 119.99999633980973, "volume": 150.58733286990608}, "properties": {}, "sites": [{"species": [{"element": "Cd", "occu": 1}], "abc": [0.8274800000000001, 0.17252, 0.75], "properties": {}, "label": "Cd", "xyz": [2.990935, -3.39298818696, 3.6445605]}, {"species": [{"element": "Cd", "occu": 1}], "abc": [0.345041, 0.17252, 0.75], "properties": {}, "label": "Cd", "xyz": [1.547991309535, -0.8937365869709999, 3.6445605]}, {"species": [{"element": "Cd", "occu": 1}], "abc": [0.8274800000000001, 0.654959, 0.75], "properties": {}, "label": "Cd", "xyz": [4.433878690465, -0.8937365869710004, 3.6445605]}, {"species": [{"element": "Cd", "occu": 1}], "abc": [0.17252, 0.8274800000000001, 0.25], "properties": {}, "label": "Cd", "xyz": [2.9909350000000003, 3.3929881869600003, 1.2148535]}, {"species": [{"element": "Cd", "occu": 1}], "abc": [0.654959, 0.8274800000000001, 0.25], "properties": {}, "label": "Cd", "xyz": [4.433878690465, 0.8937365869710007, 1.2148535]}, {"species": [{"element": "Cd", "occu": 1}], "abc": [0.17252, 0.345041, 0.25], "properties": {}, "label": "Cd", "xyz": [1.547991309535, 0.8937365869709999, 1.2148535]}, {"species": [{"element": "Os", "occu": 1}], "abc": [0.666667, 0.333333, 0.25], "properties": {}, "label": "Os", "xyz": [2.990935, -1.726820453634, 1.2148535]}, {"species": [{"element": "Os", "occu": 1}], "abc": [0.333333, 0.666667, 0.75], "properties": {}, "label": "Os", "xyz": [2.990935, 1.7268204536340002, 3.6445605]}]}}, {"@module": "pymatgen.entries.computed_entries", "@class": "ComputedStructureEntry", "energy": -0.90473076, "composition": {"Cd": 1.0}, "entry_id": "mp-1183542-GGA", "correction": 0.0, "energy_adjustments": [], "parameters": {"potcar_spec": [{"titel": "PAW_PBE Cd 06Sep2000", "hash": "0506b2d0ac28d5fe2b5ced77a701aa86", "summary_stats": null}], "run_type": "GGA", "is_hubbard": false, "hubbards": null}, "structure": {"@module": "pymatgen.core.structure", "@class": "Structure", "charge": 0, "lattice": {"matrix": [[2.6399850000000002, -1.643320999999999, 0.0], [2.6399850000000002, 1.643320999999999, 0.0], [1.617061, 0.0, 2.656151]], "pbc": [true, true, true], "a": 3.109666334072837, "b": 3.109666334072837, "c": 3.1096662863596793, "alpha": 63.80234857010674, "beta": 63.80234857010674, "gamma": 63.80234829542203, "volume": 23.04658708098534}, "properties": {}, "sites": [{"species": [{"element": "Cd", "occu": 1}], "abc": [0.0, 0.0, 0.0], "properties": {}, "label": "Cd", "xyz": [0.0, 0.0, 0.0]}]}}, {"@module": "pymatgen.entries.computed_entries", "@class": "ComputedStructureEntry", "energy": -3.55372799, "composition": {"Cd": 4.0}, "entry_id": "mp-1183591-GGA", "correction": 0.0, "energy_adjustments": [], "parameters": {"potcar_spec": [{"titel": "PAW_PBE Cd 06Sep2000", "hash": "0506b2d0ac28d5fe2b5ced77a701aa86", "summary_stats": null}], "run_type": "GGA", "is_hubbard": false, "hubbards": null}, "structure": {"@module": "pymatgen.core.structure", "@class": "Structure", "charge": 0, "lattice": {"matrix": [[1.645495, -2.850081, 0.0], [1.645495, 2.850081, 0.0], [0.0, 0.0, 9.667985]], "pbc": [true, true, true], "a": 3.2909900488433568, "b": 3.2909900488433568, "c": 9.667985, "alpha": 90.0, "beta": 90.0, "gamma": 120.00000098190831, "volume": 90.68171676877586}, "properties": {}, "sites": [{"species": [{"element": "Cd", "occu": 1}], "abc": [0.0, 0.0, 0.0], "properties": {}, "label": "Cd", "xyz": [0.0, 0.0, 0.0]}, {"species": [{"element": "Cd", "occu": 1}], "abc": [0.333333, 0.666667, 0.25], "properties": {}, "label": "Cd", "xyz": [1.645495, 0.9500289000540001, 2.41699625]}, {"species": [{"element": "Cd", "occu": 1}], "abc": [0.0, 0.0, 0.5], "properties": {}, "label": "Cd", "xyz": [0.0, 0.0, 4.8339925]}, {"species": [{"element": "Cd", "occu": 1}], "abc": [0.666667, 0.333333, 0.75], "properties": {}, "label": "Cd", "xyz": [1.645495, -0.950028900054, 7.250988749999999]}]}}, {"@module": "pymatgen.entries.computed_entries", "@class": "ComputedStructureEntry", "energy": -1.8185637, "composition": {"Cd": 2.0}, "entry_id": "mp-94-GGA", "correction": 0.0, "energy_adjustments": [], "parameters": {"potcar_spec": [{"titel": "PAW_PBE Cd 06Sep2000", "hash": "0506b2d0ac28d5fe2b5ced77a701aa86", "summary_stats": null}], "run_type": "GGA", "is_hubbard": false, "hubbards": null}, "structure": {"@module": "pymatgen.core.structure", "@class": "Structure", "charge": 0, "lattice": {"matrix": [[1.503923, -2.604871, 0.0], [1.503923, 2.604871, 0.0], [0.0, 0.0, 5.941963]], "pbc": [true, true, true], "a": 3.007845959581375, "b": 3.007845959581375, "c": 5.941963, "alpha": 90.0, "beta": 90.0, "gamma": 119.99999911096688, "volume": 46.55558206287951}, "properties": {}, "sites": [{"species": [{"element": "Cd", "occu": 1}], "abc": [0.333333, 0.666667, 0.25], "properties": {}, "label": "Cd", "xyz": [1.503923, 0.8682920699140002, 1.48549075]}, {"species": [{"element": "Cd", "occu": 1}], "abc": [0.666667, 0.333333, 0.75], "properties": {}, "label": "Cd", "xyz": [1.503923, -0.8682920699140002, 4.45647225]}]}}, {"@module": "pymatgen.entries.computed_entries", "@class": "ComputedStructureEntry", "energy": -0.92288976, "composition": {"Cd": 1.0}, "entry_id": "mp-1096861-GGA", "correction": 0.0, "energy_adjustments": [], "parameters": {"potcar_spec": [{"titel": "PAW_PBE Cd 06Sep2000", "hash": "0506b2d0ac28d5fe2b5ced77a701aa86", "summary_stats": null}], "run_type": "GGA", "is_hubbard": false, "hubbards": null}, "structure": {"@module": "pymatgen.core.structure", "@class": "Structure", "charge": 0, "lattice": {"matrix": [[0.0, 2.265485, 2.265485], [2.265485, 0.0, 2.265485], [2.265485, 2.265485, 0.0]], "pbc": [true, true, true], "a": 3.2038796123528113, "b": 3.2038796123528113, "c": 3.2038796123528113, "alpha": 60.00000000000001, "beta": 60.00000000000001, "gamma": 60.00000000000001, "volume": 23.25485140168592}, "properties": {}, "sites": [{"species": [{"element": "Cd", "occu": 1}], "abc": [0.0, 0.0, 0.0], "properties": {}, "label": "Cd", "xyz": [0.0, 0.0, 0.0]}]}}, {"@module": "pymatgen.entries.computed_entries", "@class": "ComputedStructureEntry", "energy": -0.857580599999999, "composition": {"Cd": 1.0}, "entry_id": "mp-2647135-GGA", "correction": 0.0, "energy_adjustments": [], "parameters": {"potcar_spec": [{"titel": "PAW_PBE Cd 06Sep2000", "hash": "0506b2d0ac28d5fe2b5ced77a701aa86", "summary_stats": null}], "run_type": "GGA", "is_hubbard": false, "hubbards": null}, "structure": {"@module": "pymatgen.core.structure", "@class": "Structure", "charge": 0, "lattice": {"matrix": [[-1.784322, 1.784322, 1.784322], [1.784322, -1.784322, 1.784322], [1.784322, 1.784322, -1.784322]], "pbc": [true, true, true], "a": 3.0905363610629144, "b": 3.0905363610629144, "c": 3.0905363610629144, "alpha": 109.47122063449069, "beta": 109.47122063449069, "gamma": 109.47122063449069, "volume": 22.723733218584616}, "properties": {}, "sites": [{"species": [{"element": "Cd", "occu": 1}], "abc": [0.0, 0.0, 0.0], "properties": {}, "label": "Cd", "xyz": [0.0, 0.0, 0.0]}]}}, {"@module": "pymatgen.entries.computed_entries", "@class": "ComputedStructureEntry", "energy": -58.5905479, "composition": {"Os": 8.0}, "entry_id": "mp-1180157-GGA", "correction": 0.0, "energy_adjustments": [], "parameters": {"potcar_spec": [{"titel": "PAW_PBE Os_pv 20Jan2003", "hash": "7bb96cace1809ebeb4d030d71024c5bf", "summary_stats": null}], "run_type": "GGA", "is_hubbard": false, "hubbards": null}, "structure": {"@module": "pymatgen.core.structure", "@class": "Structure", "charge": 0, "lattice": {"matrix": [[3.702065, 0.0, -0.501952], [0.0, 17.4056, 0.0], [4.947411, 0.0, 10.59575]], "pbc": [true, true, true], "a": 3.7359391154740464, "b": 17.4056, "c": 11.69387846975592, "alpha": 90.0, "beta": 72.6924733135859, "gamma": 90.0, "volume": 725.979187719575}, "properties": {}, "sites": [{"species": [{"element": "Os", "occu": 1}], "abc": [0.298208, 0.379138, 0.794986], "properties": {}, "label": "Os", "xyz": [5.0371078807659995, 6.5991243727999995, 8.273786807484]}, {"species": [{"element": "Os", "occu": 1}], "abc": [0.701792, 0.879138, 0.705013999999999], "properties": {}, "label": "Os", "xyz": [6.0860736192339955, 15.301924372799999, 7.11788619251599]}, {"species": [{"element": "Os", "occu": 1}], "abc": [0.701792, 0.620862, 0.205014], "properties": {}, "label": "Os", "xyz": [3.612368119234, 10.806475627200001, 1.8200111925160003]}, {"species": [{"element": "Os", "occu": 1}], "abc": [0.298208, 0.120862, 0.294985999999999], "properties": {}, "label": "Os", "xyz": [2.563402380765995, 2.1036756272, 2.97591180748399]}, {"species": [{"element": "Os", "occu": 1}], "abc": [0.901907999999999, 0.368738, 0.683622], "properties": {}, "label": "Os", "xyz": [6.7210810426619965, 6.4181061328, 6.790773282084]}, {"species": [{"element": "Os", "occu": 1}], "abc": [0.098092, 0.868738, 0.816377999999999], "properties": {}, "label": "Os", "xyz": [4.402100457337995, 15.1209061328, 8.60089971791599]}, {"species": [{"element": "Os", "occu": 1}], "abc": [0.098092, 0.631262, 0.316378], "properties": {}, "label": "Os", "xyz": [1.928394957338, 10.9874938672, 3.303024717916]}, {"species": [{"element": "Os", "occu": 1}], "abc": [0.901907999999999, 0.131262, 0.183621999999999], "properties": {}, "label": "Os", "xyz": [4.247375542661992, 2.2846938671999997, 1.4928982820839902]}]}}, {"@module": "pymatgen.entries.computed_entries", "@class": "ComputedStructureEntry", "energy": -87.9748755, "composition": {"Os": 8.0}, "entry_id": "mp-1080694-GGA", "correction": 0.0, "energy_adjustments": [], "parameters": {"potcar_spec": [{"titel": "PAW_PBE Os_pv 20Jan2003", "hash": "7bb96cace1809ebeb4d030d71024c5bf", "summary_stats": null}], "run_type": "GGA", "is_hubbard": false, "hubbards": null}, "structure": {"@module": "pymatgen.core.structure", "@class": "Structure", "charge": 0, "lattice": {"matrix": [[5.158646, 0.0, 0.0], [0.0, 4.6699269999999995, 0.0], [-1.420754, 0.0, 4.946648]], "pbc": [true, true, true], "a": 5.158646, "b": 4.6699269999999995, "c": 5.1466366069910165, "alpha": 90.0, "beta": 106.02488623406514, "gamma": 90.0, "volume": 119.16722482546729}, "properties": {}, "sites": [{"species": [{"element": "Os", "occu": 1}], "abc": [0.391947999999999, 0.340406, 0.791698], "properties": {}, "label": "Os", "xyz": [0.897112882115995, 1.5896711703619997, 3.916251328304]}, {"species": [{"element": "Os", "occu": 1}], "abc": [0.608051999999999, 0.840406, 0.708302], "properties": {}, "label": "Os", "xyz": [2.130402117883995, 3.9246346703619994, 3.5037206716959997]}, {"species": [{"element": "Os", "occu": 1}], "abc": [0.608051999999999, 0.659594, 0.208302], "properties": {}, "label": "Os", "xyz": [2.8407791178839954, 3.080255829638, 1.0303966716959998]}, {"species": [{"element": "Os", "occu": 1}], "abc": [0.391947999999999, 0.15959399999999901, 0.291698], "properties": {}, "label": "Os", "xyz": [1.607489882115995, 0.7452923296379953, 1.442927328304]}, {"species": [{"element": "Os", "occu": 1}], "abc": [0.861196, 0.344294, 0.640014], "properties": {}, "label": "Os", "xyz": [3.53330285006, 1.6078278465379998, 3.1659239730719997]}, {"species": [{"element": "Os", "occu": 1}], "abc": [0.138803999999999, 0.844294, 0.859985999999999], "properties": {}, "label": "Os", "xyz": [-0.5057878500600037, 3.9427913465379993, 4.254048026927995]}, {"species": [{"element": "Os", "occu": 1}], "abc": [0.138803999999999, 0.655706, 0.359986], "properties": {}, "label": "Os", "xyz": [0.20458914993999497, 3.062099153462, 1.7807240269279998]}, {"species": [{"element": "Os", "occu": 1}], "abc": [0.861196, 0.155705999999999, 0.140014], "properties": {}, "label": "Os", "xyz": [4.24367985006, 0.7271356534619953, 0.6925999730719999]}]}}, {"@module": "pymatgen.entries.computed_entries", "@class": "ComputedStructureEntry", "energy": -22.45473486, "composition": {"Os": 2.0}, "entry_id": "mp-49-GGA", "correction": 0.0, "energy_adjustments": [], "parameters": {"potcar_spec": [{"titel": "PAW_PBE Os_pv 20Jan2003", "hash": "7bb96cace1809ebeb4d030d71024c5bf", "summary_stats": null}], "run_type": "GGA", "is_hubbard": false, "hubbards": null}, "structure": {"@module": "pymatgen.core.structure", "@class": "Structure", "charge": 0, "lattice": {"matrix": [[-1.379258, -2.388944, 0.0], [-1.379258, 2.388944, 0.0], [0.0, 0.0, -4.356799]], "pbc": [true, true, true], "a": 2.7585151922184514, "b": 2.7585151922184514, "c": 4.356799, "alpha": 90.0, "beta": 90.0, "gamma": 119.99998062638922, "volume": 28.71104507864246}, "properties": {}, "sites": [{"species": [{"element": "Os", "occu": 1}], "abc": [0.333333, 0.666667, 0.25], "properties": {}, "label": "Os", "xyz": [-1.379258, 0.796316259296, -1.08919975]}, {"species": [{"element": "Os", "occu": 1}], "abc": [0.666667, 0.333333, 0.75], "properties": {}, "label": "Os", "xyz": [-1.379258, -0.7963162592960001, -3.26759925]}]}}, {"@module": "pymatgen.entries.computed_entries", "@class": "ComputedStructureEntry", "energy": -11.094008, "composition": {"Os": 1.0}, "entry_id": "mp-8643-GGA", "correction": 0.0, "energy_adjustments": [], "parameters": {"potcar_spec": [{"titel": "PAW_PBE Os_pv 20Jan2003", "hash": "7bb96cace1809ebeb4d030d71024c5bf", "summary_stats": null}], "run_type": "GGA", "is_hubbard": false, "hubbards": null}, "structure": {"@module": "pymatgen.core.structure", "@class": "Structure", "charge": 0, "lattice": {"matrix": [[0.0, 1.931725999999999, 1.931725999999999], [1.931725999999999, 0.0, 1.931725999999999], [1.931725999999999, 1.931725999999999, 0.0]], "pbc": [true, true, true], "a": 2.731873107988728, "b": 2.731873107988728, "c": 2.731873107988728, "alpha": 60.00000000000001, "beta": 60.00000000000001, "gamma": 60.00000000000001, "volume": 14.416723572383827}, "properties": {}, "sites": [{"species": [{"element": "Os", "occu": 1}], "abc": [0.0, 0.0, 0.0], "properties": {}, "label": "Os", "xyz": [0.0, 0.0, 0.0]}]}}, {"@module": "pymatgen.entries.computed_entries", "@class": "ComputedStructureEntry", "energy": -10.34453835, "composition": {"Os": 1.0}, "entry_id": "mp-2647031-GGA", "correction": 0.0, "energy_adjustments": [], "parameters": {"potcar_spec": [{"titel": "PAW_PBE Os_pv 20Jan2003", "hash": "7bb96cace1809ebeb4d030d71024c5bf", "summary_stats": null}], "run_type": "GGA", "is_hubbard": false, "hubbards": null}, "structure": {"@module": "pymatgen.core.structure", "@class": "Structure", "charge": 0, "lattice": {"matrix": [[-1.549032, 1.549032, 1.549032], [1.549032, -1.549032, 1.549032], [1.549032, 1.549032, -1.549032]], "pbc": [true, true, true], "a": 2.6830021265500332, "b": 2.6830021265500332, "c": 2.6830021265500332, "alpha": 109.47122063449069, "beta": 109.47122063449069, "gamma": 109.47122063449069, "volume": 14.867609985018243}, "properties": {}, "sites": [{"species": [{"element": "Os", "occu": 1}], "abc": [0.0, 0.0, 0.0], "properties": {}, "label": "Os", "xyz": [0.0, 0.0, 0.0]}]}}]