[{"@module": "pymatgen.entries.computed_entries", "@class": "ComputedStructureEntry", "energy": -11.86617831, "composition": {"Ce": 2.0}, "entry_id": "mp-567332-GGA", "correction": 0.0, "energy_adjustments": [], "parameters": {"potcar_spec": [{"titel": "PAW_PBE Ce 28Sep2000", "hash": "ff3a09f2ff91798e58eb4b9854e9be4a", "summary_stats": null}], "run_type": "GGA", "is_hubbard": false, "hubbards": null}, "structure": {"@module": "pymatgen.core.structure", "@class": "Structure", "charge": 0, "lattice": {"matrix": [[1.6621100000000002, 2.885653999999999, 0.0], [-1.6621100000000002, 2.885653999999999, 0.0], [0.0, 1.927671999999999, 5.439661]], "pbc": [true, true, true], "a": 3.3301064036778154, "b": 3.3301064036778154, "c": 5.771120440131622, "alpha": 73.17554353376278, "beta": 73.17554353376278, "gamma": 59.883088799912606, "volume": 52.18021327092437}, "properties": {}, "sites": [{"species": [{"element": "Ce", "occu": 1}], "abc": [0.744638999999999, 0.744638999999999, 0.24950499999999903], "properties": {}, "label": "Ce", "xyz": [4.150340778608116e-17, 4.778504820171991, 1.3572226178049949]}, {"species": [{"element": "Ce", "occu": 1}], "abc": [0.255361, 0.255361, 0.750494999999999], "properties": {}, "label": "Ce", "xyz": [-2.729976952053903e-17, 2.9204751798279966, 4.0824383821949946]}]}}, {"@module": "pymatgen.entries.computed_entries", "@class": "ComputedStructureEntry", "energy": -11.70335139, "composition": {"Ce": 2.0}, "entry_id": "mp-20736-GGA", "correction": 0.0, "energy_adjustments": [], "parameters": {"potcar_spec": [{"titel": "PAW_PBE Ce 28Sep2000", "hash": "ff3a09f2ff91798e58eb4b9854e9be4a", "summary_stats": null}], "run_type": "GGA", "is_hubbard": false, "hubbards": null}, "structure": {"@module": "pymatgen.core.structure", "@class": "Structure", "charge": 0, "lattice": {"matrix": [[-1.630513, -2.824131, 0.0], [-1.630513, 2.824131, 0.0], [0.0, 0.0, -5.756325]], "pbc": [true, true, true], "a": 3.2610256896151553, "b": 3.2610256896151553, "c": 5.756325, "alpha": 90.0, "beta": 90.0, "gamma": 119.99999370293328, "volume": 53.01324705204593}, "properties": {}, "sites": [{"species": [{"element": "Ce", "occu": 1}], "abc": [0.333333, 0.666667, 0.75], "properties": {}, "label": "Ce", "xyz": [-1.630513, 0.941378882754, -4.31724375]}, {"species": [{"element": "Ce", "occu": 1}], "abc": [0.666667, 0.333333, 0.25], "properties": {}, "label": "Ce", "xyz": [-1.630513, -0.941378882754, -1.43908125]}]}}, {"@module": "pymatgen.entries.computed_entries", "@class": "ComputedStructureEntry", "energy": -23.56100087, "composition": {"Ce": 4.0}, "entry_id": "mp-20372-GGA", "correction": 0.0, "energy_adjustments": [], "parameters": {"potcar_spec": [{"titel": "PAW_PBE Ce 28Sep2000", "hash": "ff3a09f2ff91798e58eb4b9854e9be4a", "summary_stats": null}], "run_type": "GGA", "is_hubbard": false, "hubbards": null}, "structure": {"@module": "pymatgen.core.structure", "@class": "Structure", "charge": 0, "lattice": {"matrix": [[1.684737, -2.918049, 0.0], [1.684737, 2.918049, 0.0], [0.0, 0.0, 11.173904]], "pbc": [true, true, true], "a": 3.3694730634878205, "b": 3.3694730634878205, "c": 11.173904, "alpha": 90.0, "beta": 90.0, "gamma": 119.99998161162034, "volume": 109.86506719972664}, "properties": {}, "sites": [{"species": [{"element": "Ce", "occu": 1}], "abc": [0.0, 0.0, 0.0], "properties": {}, "label": "Ce", "xyz": [0.0, 0.0, 0.0]}, {"species": [{"element": "Ce", "occu": 1}], "abc": [0.333333, 0.666667, 0.25], "properties": {}, "label": "Ce", "xyz": [1.684737, 0.972684945366, 2.793476]}, {"species": [{"element": "Ce", "occu": 1}], "abc": [0.0, 0.0, 0.5], "properties": {}, "label": "Ce", "xyz": [0.0, 0.0, 5.586952]}, {"species": [{"element": "Ce", "occu": 1}], "abc": [0.666667, 0.333333, 0.75], "properties": {}, "label": "Ce", "xyz": [1.684737, -0.9726849453659999, 8.380428]}]}}, {"@module": "pymatgen.entries.computed_entries", "@class": "ComputedStructureEntry", "energy": -5.93152909, "composition": {"Ce": 1.0}, "entry_id": "mp-28-GGA", "correction": 0.0, "energy_adjustments": [], "parameters": {"potcar_spec": [{"titel": "PAW_PBE Ce 28Sep2000", "hash": "ff3a09f2ff91798e58eb4b9854e9be4a", "summary_stats": null}], "run_type": "GGA", "is_hubbard": false, "hubbards": null}, "structure": {"@module": "pymatgen.core.structure", "@class": "Structure", "charge": 0, "lattice": {"matrix": [[0.0, 2.360218, 2.360218], [2.360218, 0.0, 2.360218], [2.360218, 2.360218, 0.0]], "pbc": [true, true, true], "a": 3.3378523057571017, "b": 3.3378523057571017, "c": 3.3378523057571017, "alpha": 60.00000000000001, "beta": 60.00000000000001, "gamma": 60.00000000000001, "volume": 26.295797709760564}, "properties": {}, "sites": [{"species": [{"element": "Ce", "occu": 1}], "abc": [0.0, 0.0, 0.0], "properties": {}, "label": "Ce", "xyz": [0.0, 0.0, 0.0]}]}}, {"@module": "pymatgen.entries.computed_entries", "@class": "ComputedStructureEntry", "energy": -5.70483875, "composition": {"Ce": 1.0}, "entry_id": "mp-10024-GGA", "correction": 0.0, "energy_adjustments": [], "parameters": {"potcar_spec": [{"titel": "PAW_PBE Ce 28Sep2000", "hash": "ff3a09f2ff91798e58eb4b9854e9be4a", "summary_stats": null}], "run_type": "GGA", "is_hubbard": false, "hubbards": null}, "structure": {"@module": "pymatgen.core.structure", "@class": "Structure", "charge": 0, "lattice": {"matrix": [[-1.887976, 1.887976, 1.887976], [1.887976, -1.887976, 1.887976], [1.887976, 1.887976, -1.887976]], "pbc": [true, true, true], "a": 3.2700703554706587, "b": 3.2700703554706587, "c": 3.2700703554706587, "alpha": 109.47122063449069, "beta": 109.47122063449069, "gamma": 109.47122063449069, "volume": 26.918409712377805}, "properties": {}, "sites": [{"species": [{"element": "Ce", "occu": 1}], "abc": [0.0, 0.0, 0.0], "properties": {}, "label": "Ce", "xyz": [0.0, 0.0, 0.0]}]}}, {"@module": "pymatgen.entries.computed_entries", "@class": "ComputedStructureEntry", "energy": -11.78685384, "composition": {"Ce": 2.0}, "entry_id": "mp-64-GGA", "correction": 0.0, "energy_adjustments": [], "parameters": {"potcar_spec": [{"titel": "PAW_PBE Ce 28Sep2000", "hash": "ff3a09f2ff91798e58eb4b9854e9be4a", "summary_stats": null}], "run_type": "GGA", "is_hubbard": false, "hubbards": null}, "structure": {"@module": "pymatgen.core.structure", "@class": "Structure", "charge": 0, "lattice": {"matrix": [[1.593703, -3.08621, 0.0], [1.593703, 3.08621, 0.0], [0.0, 0.0, 5.281438]], "pbc": [true, true, true], "a": 3.4734106316859514, "b": 3.4734106316859514, "c": 5.281438, "alpha": 90.0, "beta": 90.0, "gamma": 125.37680370975387, "volume": 51.95352816439487}, "properties": {}, "sites": [{"species": [{"element": "Ce", "occu": 1}], "abc": [0.899037, 0.100963, 0.75], "properties": {}, "label": "Ce", "xyz": [1.593703, -2.4630239595399996, 3.9610784999999997]}, {"species": [{"element": "Ce", "occu": 1}], "abc": [0.100963, 0.899037, 0.25], "properties": {}, "label": "Ce", "xyz": [1.593703, 2.46302395954, 1.3203595]}]}}, {"@module": "pymatgen.entries.computed_entries", "@class": "ComputedStructureEntry", "energy": -8.80854029, "composition": {"Ce": 1.0, "Tl": 1.0}, "entry_id": "mp-1206755-GGA", "correction": 0.0, "energy_adjustments": [], "parameters": {"potcar_spec": [{"titel": "PAW_PBE Ce 28Sep2000", "hash": "ff3a09f2ff91798e58eb4b9854e9be4a", "summary_stats": null}, {"titel": "PAW_PBE Tl_d 06Sep2000", "hash": "78590fbb9adc26deddfa2c1440ce2524", "summary_stats": null}], "run_type": "GGA", "is_hubbard": false, "hubbards": null}, "structure": {"@module": "pymatgen.core.structure", "@class": "Structure", "charge": 0, "lattice": {"matrix": [[3.511539, 0.0, 0.0], [0.0, 3.511539, 0.0], [0.0, 0.0, 4.660654]], "pbc": [true, true, true], "a": 3.511539, "b": 3.511539, "c": 4.660654, "alpha": 90.0, "beta": 90.0, "gamma": 90.0, "volume": 57.47008706472899}, "properties": {}, "sites": [{"species": [{"element": "Ce", "occu": 1}], "abc": [0.0, 0.0, 0.0], "properties": {}, "label": "Ce", "xyz": [0.0, 0.0, 0.0]}, {"species": [{"element": "Tl", "occu": 1}], "abc": [0.5, 0.5, 0.5], "properties": {}, "label": "Tl", "xyz": [1.7557695, 1.7557695, 2.330327]}]}}, {"@module": "pymatgen.entries.computed_entries", "@class": "ComputedStructureEntry", "energy": -8.72024729, "composition": {"Ce": 1.0, "Tl": 1.0}, "entry_id": "mp-1206752-GGA", "correction": 0.0, "energy_adjustments": [], "parameters": {"potcar_spec": [{"titel": "PAW_PBE Ce 28Sep2000", "hash": "ff3a09f2ff91798e58eb4b9854e9be4a", "summary_stats": null}, {"titel": "PAW_PBE Tl_d 06Sep2000", "hash": "78590fbb9adc26deddfa2c1440ce2524", "summary_stats": null}], "run_type": "GGA", "is_hubbard": false, "hubbards": null}, "structure": {"@module": "pymatgen.core.structure", "@class": "Structure", "charge": 0, "lattice": {"matrix": [[3.886390999999999, 0.0, 0.0], [0.0, 3.886390999999999, 0.0], [0.0, 0.0, 3.886390999999999]], "pbc": [true, true, true], "a": 3.886390999999999, "b": 3.886390999999999, "c": 3.886390999999999, "alpha": 90.0, "beta": 90.0, "gamma": 90.0, "volume": 58.70018570665442}, "properties": {}, "sites": [{"species": [{"element": "Ce", "occu": 1}], "abc": [0.0, 0.0, 0.0], "properties": {}, "label": "Ce", "xyz": [0.0, 0.0, 0.0]}, {"species": [{"element": "Tl", "occu": 1}], "abc": [0.5, 0.5, 0.5], "properties": {}, "label": "Tl", "xyz": [1.9431954999999994, 1.9431954999999994, 1.9431954999999994]}]}}, {"@module": "pymatgen.entries.computed_entries", "@class": "ComputedStructureEntry", "energy": -13.97952422, "composition": {"Ce": 1.0, "Tl": 3.0}, "entry_id": "mp-20603-GGA", "correction": 0.0, "energy_adjustments": [], "parameters": {"potcar_spec": [{"titel": "PAW_PBE Ce 28Sep2000", "hash": "ff3a09f2ff91798e58eb4b9854e9be4a", "summary_stats": null}, {"titel": "PAW_PBE Tl_d 06Sep2000", "hash": "78590fbb9adc26deddfa2c1440ce2524", "summary_stats": null}], "run_type": "GGA", "is_hubbard": false, "hubbards": null}, "structure": {"@module": "pymatgen.core.structure", "@class": "Structure", "charge": 0, "lattice": {"matrix": [[4.826137, 0.0, 0.0], [0.0, 4.826137, 0.0], [0.0, 0.0, 4.826137]], "pbc": [true, true, true], "a": 4.826137, "b": 4.826137, "c": 4.826137, "alpha": 90.0, "beta": 90.0, "gamma": 90.0, "volume": 112.40844455117616}, "properties": {}, "sites": [{"species": [{"element": "Ce", "occu": 1}], "abc": [0.0, 0.0, 0.0], "properties": {}, "label": "Ce", "xyz": [0.0, 0.0, 0.0]}, {"species": [{"element": "Tl", "occu": 1}], "abc": [0.0, 0.5, 0.5], "properties": {}, "label": "Tl", "xyz": [0.0, 2.4130685, 2.4130685]}, {"species": [{"element": "Tl", "occu": 1}], "abc": [0.5, 0.5, 0.0], "properties": {}, "label": "Tl", "xyz": [2.4130685, 2.4130685, 0.0]}, {"species": [{"element": "Tl", "occu": 1}], "abc": [0.5, 0.0, 0.5], "properties": {}, "label": "Tl", "xyz": [2.4130685, 0.0, 2.4130685]}]}}, {"@module": "pymatgen.entries.computed_entries", "@class": "ComputedStructureEntry", "energy": -20.70117878, "composition": {"Ce": 3.0, "Tl": 1.0}, "entry_id": "mp-21412-GGA", "correction": 0.0, "energy_adjustments": [], "parameters": {"potcar_spec": [{"titel": "PAW_PBE Ce 28Sep2000", "hash": "ff3a09f2ff91798e58eb4b9854e9be4a", "summary_stats": null}, {"titel": "PAW_PBE Tl_d 06Sep2000", "hash": "78590fbb9adc26deddfa2c1440ce2524", "summary_stats": null}], "run_type": "GGA", "is_hubbard": false, "hubbards": null}, "structure": {"@module": "pymatgen.core.structure", "@class": "Structure", "charge": 0, "lattice": {"matrix": [[4.841175, 0.0, 0.0], [0.0, 4.841175, 0.0], [0.0, 0.0, 4.841175]], "pbc": [true, true, true], "a": 4.841175, "b": 4.841175, "c": 4.841175, "alpha": 90.0, "beta": 90.0, "gamma": 90.0, "volume": 113.46249928829721}, "properties": {}, "sites": [{"species": [{"element": "Ce", "occu": 1}], "abc": [0.0, 0.5, 0.5], "properties": {}, "label": "Ce", "xyz": [0.0, 2.4205875, 2.4205875]}, {"species": [{"element": "Ce", "occu": 1}], "abc": [0.5, 0.5, 0.0], "properties": {}, "label": "Ce", "xyz": [2.4205875, 2.4205875, 0.0]}, {"species": [{"element": "Ce", "occu": 1}], "abc": [0.5, 0.0, 0.5], "properties": {}, "label": "Ce", "xyz": [2.4205875, 0.0, 2.4205875]}, {"species": [{"element": "Tl", "occu": 1}], "abc": [0.0, 0.0, 0.0], "properties": {}, "label": "Tl", "xyz": [0.0, 0.0, 0.0]}]}}, {"@module": "pymatgen.entries.computed_entries", "@class": "ComputedStructureEntry", "energy": -7.08792944, "composition": {"Tl": 3.0}, "entry_id": "mp-972351-GGA", "correction": 0.0, "energy_adjustments": [], "parameters": {"potcar_spec": [{"titel": "PAW_PBE Tl_d 06Sep2000", "hash": "78590fbb9adc26deddfa2c1440ce2524", "summary_stats": null}], "run_type": "GGA", "is_hubbard": false, "hubbards": null}, "structure": {"@module": "pymatgen.core.structure", "@class": "Structure", "charge": 0, "lattice": {"matrix": [[8.303442, -1.825894, 0.0], [8.303442, 1.825894, 0.0], [7.901935, 0.0, 3.136951]], "pbc": [true, true, true], "a": 8.501825565524149, "b": 8.501825565524149, "c": 8.501825587520953, "alpha": 24.803476215015333, "beta": 24.803476215015333, "gamma": 24.803473649722516, "volume": 95.11991391484369}, "properties": {}, "sites": [{"species": [{"element": "Tl", "occu": 1}], "abc": [0.0, 0.0, 0.0], "properties": {}, "label": "Tl", "xyz": [0.0, 0.0, 0.0]}, {"species": [{"element": "Tl", "occu": 1}], "abc": [0.220598, 0.220598, 0.220598], "properties": {}, "label": "Tl", "xyz": [5.406596453762, -7.966680104942724e-18, 0.6920051166979999]}, {"species": [{"element": "Tl", "occu": 1}], "abc": [0.779401999999999, 0.779401999999999, 0.779401999999999], "properties": {}, "label": "Tl", "xyz": [19.10222254623798, 1.05676550958834e-17, 2.444945883301997]}]}}, {"@module": "pymatgen.entries.computed_entries", "@class": "ComputedStructureEntry", "energy": -4.71752371, "composition": {"Tl": 2.0}, "entry_id": "mp-82-GGA", "correction": 0.0, "energy_adjustments": [], "parameters": {"potcar_spec": [{"titel": "PAW_PBE Tl_d 06Sep2000", "hash": "78590fbb9adc26deddfa2c1440ce2524", "summary_stats": null}], "run_type": "GGA", "is_hubbard": false, "hubbards": null}, "structure": {"@module": "pymatgen.core.structure", "@class": "Structure", "charge": 0, "lattice": {"matrix": [[1.774462, -3.073459, 0.0], [1.774462, 3.073459, 0.0], [0.0, 0.0, 5.738414]], "pbc": [true, true, true], "a": 3.5489245714899322, "b": 3.5489245714899322, "c": 5.738414, "alpha": 90.0, "beta": 90.0, "gamma": 120.00001065378194, "volume": 62.591592371346565}, "properties": {}, "sites": [{"species": [{"element": "Tl", "occu": 1}], "abc": [0.333333, 0.666667, 0.75], "properties": {}, "label": "Tl", "xyz": [1.774462, 1.024488382306, 4.3038105]}, {"species": [{"element": "Tl", "occu": 1}], "abc": [0.666667, 0.333333, 0.25], "properties": {}, "label": "Tl", "xyz": [1.774462, -1.0244883823060003, 1.4346035]}]}}, {"@module": "pymatgen.entries.computed_entries", "@class": "ComputedStructureEntry", "energy": -9.34650321, "composition": {"Tl": 4.0}, "entry_id": "mp-972373-GGA", "correction": 0.0, "energy_adjustments": [], "parameters": {"potcar_spec": [{"titel": "PAW_PBE Tl_d 06Sep2000", "hash": "78590fbb9adc26deddfa2c1440ce2524", "summary_stats": null}], "run_type": "GGA", "is_hubbard": false, "hubbards": null}, "structure": {"@module": "pymatgen.core.structure", "@class": "Structure", "charge": 0, "lattice": {"matrix": [[1.77277, -3.070527, 0.0], [1.77277, 3.070527, 0.0], [0.0, 0.0, 11.435646]], "pbc": [true, true, true], "a": 3.5455393850060384, "b": 3.5455393850060384, "c": 11.435646, "alpha": 90.0, "beta": 90.0, "gamma": 119.99998852426396, "volume": 124.49617627858683}, "properties": {}, "sites": [{"species": [{"element": "Tl", "occu": 1}], "abc": [0.0, 0.0, 0.0], "properties": {}, "label": "Tl", "xyz": [0.0, 0.0, 0.0]}, {"species": [{"element": "Tl", "occu": 1}], "abc": [0.333333, 0.666667, 0.25], "properties": {}, "label": "Tl", "xyz": [1.77277, 1.0235110470179998, 2.8589115]}, {"species": [{"element": "Tl", "occu": 1}], "abc": [0.0, 0.0, 0.5], "properties": {}, "label": "Tl", "xyz": [0.0, 0.0, 5.717823]}, {"species": [{"element": "Tl", "occu": 1}], "abc": [0.666667, 0.333333, 0.75], "properties": {}, "label": "Tl", "xyz": [1.77277, -1.0235110470179998, 8.5767345]}]}}, {"@module": "pymatgen.entries.computed_entries", "@class": "ComputedStructureEntry", "energy": -68.4161854, "composition": {"Tl": 29.0}, "entry_id": "mp-1187790-GGA", "correction": 0.0, "energy_adjustments": [], "parameters": {"potcar_spec": [{"titel": "PAW_PBE Tl_d 06Sep2000", "hash": "78590fbb9adc26deddfa2c1440ce2524", "summary_stats": null}], "run_type": "GGA", "is_hubbard": false, "hubbards": null}, "structure": {"@module": "pymatgen.core.structure", "@class": "Structure", "charge": 0, "lattice": {"matrix": [[-6.126998, 6.126998, 6.126998], [6.126998, -6.126998, 6.126998], [6.126998, 6.126998, -6.126998]], "pbc": [true, true, true], "a": 10.612271833872898, "b": 10.612271833872898, "c": 10.612271833872898, "alpha": 109.47122063449069, "beta": 109.47122063449069, "gamma": 109.47122063449069, "volume": 920.0325805691983}, "properties": {}, "sites": [{"species": [{"element": "Tl", "occu": 1}], "abc": [0.0, 0.0, 0.363429], "properties": {}, "label": "Tl", "xyz": [2.226728756142, 2.226728756142, -2.226728756142]}, {"species": [{"element": "Tl", "occu": 1}], "abc": [0.0, 0.0, 0.0], "properties": {}, "label": "Tl", "xyz": [0.0, 0.0, 0.0]}, {"species": [{"element": "Tl", "occu": 1}], "abc": [0.0, 0.317121999999999, 0.598436], "properties": {}, "label": "Tl", "xyz": [5.609622034883994, 1.723610315372006, -1.723610315372006]}, {"species": [{"element": "Tl", "occu": 1}], "abc": [0.0, 0.363429, 0.0], "properties": {}, "label": "Tl", "xyz": [2.226728756142, -2.226728756142, 2.226728756142]}, {"species": [{"element": "Tl", "occu": 1}], "abc": [0.0, 0.598436, 0.317121999999999], "properties": {}, "label": "Tl", "xyz": [5.609622034883994, -1.723610315372006, 1.723610315372006]}, {"species": [{"element": "Tl", "occu": 1}], "abc": [0.0, 0.625784, 0.809041], "properties": {}, "label": "Tl", "xyz": [8.791169905350001, 1.1228152724860003, -1.1228152724860003]}, {"species": [{"element": "Tl", "occu": 1}], "abc": [0.0, 0.809041, 0.625784], "properties": {}, "label": "Tl", "xyz": [8.791169905350001, -1.1228152724859999, 1.1228152724859999]}, {"species": [{"element": "Tl", "occu": 1}], "abc": [0.816743, 0.190959, 0.190959], "properties": {}, "label": "Tl", "xyz": [-2.66417190535, 5.004182727514, 5.004182727514]}, {"species": [{"element": "Tl", "occu": 1}], "abc": [0.809041, 0.0, 0.625784], "properties": {}, "label": "Tl", "xyz": [-1.1228152724859999, 8.791169905350001, 1.1228152724859999]}, {"species": [{"element": "Tl", "occu": 1}], "abc": [0.809041, 0.625784, 0.0], "properties": {}, "label": "Tl", "xyz": [-1.1228152724859999, 1.1228152724859999, 8.791169905350001]}, {"species": [{"element": "Tl", "occu": 1}], "abc": [0.718685999999999, 0.401564, 0.401564], "properties": {}, "label": "Tl", "xyz": [0.5173759651160053, 4.403387684627995, 4.403387684627995]}, {"species": [{"element": "Tl", "occu": 1}], "abc": [0.682878, 0.682878, 0.281314], "properties": {}, "label": "Tl", "xyz": [1.723610315372, 1.7236103153720004, 6.644373965116]}, {"species": [{"element": "Tl", "occu": 1}], "abc": [0.682878, 0.281314, 0.682878], "properties": {}, "label": "Tl", "xyz": [1.7236103153720002, 6.644373965116, 1.7236103153720006]}, {"species": [{"element": "Tl", "occu": 1}], "abc": [0.636571, 0.636571, 0.636571], "properties": {}, "label": "Tl", "xyz": [3.9002692438580002, 3.9002692438580002, 3.9002692438580002]}, {"species": [{"element": "Tl", "occu": 1}], "abc": [0.625784, 0.809041, 0.0], "properties": {}, "label": "Tl", "xyz": [1.1228152724860003, -1.1228152724860003, 8.791169905350001]}, {"species": [{"element": "Tl", "occu": 1}], "abc": [0.625784, 0.0, 0.809041], "properties": {}, "label": "Tl", "xyz": [1.1228152724860003, 8.791169905350001, -1.1228152724860003]}, {"species": [{"element": "Tl", "occu": 1}], "abc": [0.598436, 0.0, 0.317121999999999], "properties": {}, "label": "Tl", "xyz": [-1.723610315372006, 5.609622034883994, 1.723610315372006]}, {"species": [{"element": "Tl", "occu": 1}], "abc": [0.598436, 0.317121999999999, 0.0], "properties": {}, "label": "Tl", "xyz": [-1.723610315372006, 1.723610315372006, 5.609622034883994]}, {"species": [{"element": "Tl", "occu": 1}], "abc": [0.401564, 0.401564, 0.718685999999999], "properties": {}, "label": "Tl", "xyz": [4.403387684627995, 4.403387684627995, 0.5173759651160055]}, {"species": [{"element": "Tl", "occu": 1}], "abc": [0.401564, 0.718685999999999, 0.401564], "properties": {}, "label": "Tl", "xyz": [4.403387684627995, 0.5173759651160055, 4.403387684627995]}, {"species": [{"element": "Tl", "occu": 1}], "abc": [0.374216, 0.374216, 0.183257], "properties": {}, "label": "Tl", "xyz": [1.1228152724859999, 1.1228152724860003, 3.4628260946500005]}, {"species": [{"element": "Tl", "occu": 1}], "abc": [0.374216, 0.183257, 0.374216], "properties": {}, "label": "Tl", "xyz": [1.1228152724859999, 3.4628260946500005, 1.1228152724860003]}, {"species": [{"element": "Tl", "occu": 1}], "abc": [0.363429, 0.0, 0.0], "properties": {}, "label": "Tl", "xyz": [-2.226728756142, 2.226728756142, 2.226728756142]}, {"species": [{"element": "Tl", "occu": 1}], "abc": [0.317121999999999, 0.598436, 0.0], "properties": {}, "label": "Tl", "xyz": [1.723610315372006, -1.723610315372006, 5.609622034883994]}, {"species": [{"element": "Tl", "occu": 1}], "abc": [0.317121999999999, 0.0, 0.598436], "properties": {}, "label": "Tl", "xyz": [1.723610315372006, 5.609622034883994, -1.723610315372006]}, {"species": [{"element": "Tl", "occu": 1}], "abc": [0.281314, 0.682878, 0.682878], "properties": {}, "label": "Tl", "xyz": [6.644373965116, 1.7236103153720002, 1.7236103153720006]}, {"species": [{"element": "Tl", "occu": 1}], "abc": [0.190959, 0.190959, 0.816743], "properties": {}, "label": "Tl", "xyz": [5.004182727514, 5.004182727514, -2.6641719053500004]}, {"species": [{"element": "Tl", "occu": 1}], "abc": [0.190959, 0.816743, 0.190959], "properties": {}, "label": "Tl", "xyz": [5.004182727514, -2.6641719053500004, 5.004182727514]}, {"species": [{"element": "Tl", "occu": 1}], "abc": [0.183257, 0.374216, 0.374216], "properties": {}, "label": "Tl", "xyz": [3.46282609465, 1.122815272486, 1.1228152724860003]}]}}, {"@module": "pymatgen.entries.computed_entries", "@class": "ComputedStructureEntry", "energy": -2.3519535400000002, "composition": {"Tl": 1.0}, "entry_id": "mp-151-GGA", "correction": 0.0, "energy_adjustments": [], "parameters": {"potcar_spec": [{"titel": "PAW_PBE Tl_d 06Sep2000", "hash": "78590fbb9adc26deddfa2c1440ce2524", "summary_stats": null}], "run_type": "GGA", "is_hubbard": false, "hubbards": null}, "structure": {"@module": "pymatgen.core.structure", "@class": "Structure", "charge": 0, "lattice": {"matrix": [[-2.4966, -2.4966, 0.0], [-2.4966, 0.0, -2.4966], [0.0, -2.4966, -2.4966]], "pbc": [true, true, true], "a": 3.530725579820669, "b": 3.530725579820669, "c": 3.530725579820669, "alpha": 60.00000000000001, "beta": 60.00000000000001, "gamma": 60.00000000000001, "volume": 31.122673321391996}, "properties": {}, "sites": [{"species": [{"element": "Tl", "occu": 1}], "abc": [0.0, 0.0, 0.0], "properties": {}, "label": "Tl", "xyz": [0.0, 0.0, 0.0]}]}}, {"@module": "pymatgen.entries.computed_entries", "@class": "ComputedStructureEntry", "energy": -2.36165298, "composition": {"Tl": 1.0}, "entry_id": "mp-39-GGA", "correction": 0.0, "energy_adjustments": [], "parameters": {"potcar_spec": [{"titel": "PAW_PBE Tl_d 06Sep2000", "hash": "78590fbb9adc26deddfa2c1440ce2524", "summary_stats": null}], "run_type": "GGA", "is_hubbard": false, "hubbards": null}, "structure": {"@module": "pymatgen.core.structure", "@class": "Structure", "charge": 0, "lattice": {"matrix": [[-1.98177, 1.98177, 1.98177], [1.98177, -1.98177, 1.98177], [1.98177, 1.98177, -1.98177]], "pbc": [true, true, true], "a": 3.432526328915774, "b": 3.432526328915774, "c": 3.432526328915774, "alpha": 109.47122063449069, "beta": 109.47122063449069, "gamma": 109.47122063449069, "volume": 31.132911755884933}, "properties": {}, "sites": [{"species": [{"element": "Tl", "occu": 1}], "abc": [0.0, 0.0, 0.0], "properties": {}, "label": "Tl", "xyz": [0.0, 0.0, 0.0]}]}}]